{"frames":{"h3 (9).png":{"frame":{"x":2,"y":2,"w":253,"h":261},"rotated":false,"trimmed":true,"spriteSourceSize":{"x":66,"y":67,"w":253,"h":261},"sourceSize":{"w":383,"h":393}},"h3 (8).png":{"frame":{"x":257,"y":2,"w":253,"h":260},"rotated":false,"trimmed":true,"spriteSourceSize":{"x":66,"y":68,"w":253,"h":260},"sourceSize":{"w":383,"h":393}},"h3 (7).png":{"frame":{"x":2,"y":265,"w":253,"h":260},"rotated":true,"trimmed":true,"spriteSourceSize":{"x":66,"y":68,"w":253,"h":260},"sourceSize":{"w":383,"h":393}},"h3 (6).png":{"frame":{"x":512,"y":2,"w":253,"h":259},"rotated":false,"trimmed":true,"spriteSourceSize":{"x":66,"y":69,"w":253,"h":259},"sourceSize":{"w":383,"h":393}},"h3 (5).png":{"frame":{"x":264,"y":264,"w":253,"h":259},"rotated":true,"trimmed":true,"spriteSourceSize":{"x":66,"y":69,"w":253,"h":259},"sourceSize":{"w":383,"h":393}},"h3 (4).png":{"frame":{"x":2,"y":520,"w":253,"h":258},"rotated":true,"trimmed":true,"spriteSourceSize":{"x":66,"y":70,"w":253,"h":258},"sourceSize":{"w":383,"h":393}},"h3 (36).png":{"frame":{"x":262,"y":520,"w":253,"h":258},"rotated":true,"trimmed":true,"spriteSourceSize":{"x":66,"y":70,"w":253,"h":258},"sourceSize":{"w":383,"h":393}},"h3 (35).png":{"frame":{"x":522,"y":519,"w":254,"h":258},"rotated":true,"trimmed":true,"spriteSourceSize":{"x":66,"y":70,"w":254,"h":258},"sourceSize":{"w":383,"h":393}},"h3 (34).png":{"frame":{"x":2,"y":775,"w":255,"h":258},"rotated":true,"trimmed":true,"spriteSourceSize":{"x":66,"y":70,"w":255,"h":258},"sourceSize":{"w":383,"h":393}},"h3 (33).png":{"frame":{"x":262,"y":775,"w":255,"h":258},"rotated":true,"trimmed":true,"spriteSourceSize":{"x":66,"y":70,"w":255,"h":258},"sourceSize":{"w":383,"h":393}},"h3 (32).png":{"frame":{"x":782,"y":2,"w":257,"h":258},"rotated":true,"trimmed":true,"spriteSourceSize":{"x":66,"y":70,"w":257,"h":258},"sourceSize":{"w":383,"h":393}},"h3 (31).png":{"frame":{"x":782,"y":261,"w":259,"h":258},"rotated":false,"trimmed":true,"spriteSourceSize":{"x":66,"y":70,"w":259,"h":258},"sourceSize":{"w":383,"h":393}},"h3 (30).png":{"frame":{"x":782,"y":521,"w":260,"h":258},"rotated":false,"trimmed":true,"spriteSourceSize":{"x":66,"y":70,"w":260,"h":258},"sourceSize":{"w":383,"h":393}},"h3 (3).png":{"frame":{"x":522,"y":775,"w":252,"h":258},"rotated":true,"trimmed":true,"spriteSourceSize":{"x":66,"y":70,"w":252,"h":258},"sourceSize":{"w":383,"h":393}},"h3 (29).png":{"frame":{"x":2,"y":1032,"w":325,"h":331},"rotated":true,"trimmed":true,"spriteSourceSize":{"x":35,"y":37,"w":325,"h":331},"sourceSize":{"w":383,"h":393}},"h3 (28).png":{"frame":{"x":782,"y":781,"w":333,"h":360},"rotated":true,"trimmed":true,"spriteSourceSize":{"x":29,"y":26,"w":333,"h":360},"sourceSize":{"w":383,"h":393}},"h3 (27).png":{"frame":{"x":1144,"y":2,"w":340,"h":365},"rotated":true,"trimmed":true,"spriteSourceSize":{"x":25,"y":26,"w":340,"h":365},"sourceSize":{"w":383,"h":393}},"h3 (26).png":{"frame":{"x":1044,"y":344,"w":350,"h":360},"rotated":false,"trimmed":true,"spriteSourceSize":{"x":20,"y":26,"w":350,"h":360},"sourceSize":{"w":383,"h":393}},"h3 (25).png":{"frame":{"x":1144,"y":706,"w":353,"h":361},"rotated":true,"trimmed":true,"spriteSourceSize":{"x":20,"y":27,"w":353,"h":361},"sourceSize":{"w":383,"h":393}},"h3 (24).png":{"frame":{"x":2,"y":1359,"w":358,"h":362},"rotated":true,"trimmed":true,"spriteSourceSize":{"x":17,"y":27,"w":358,"h":362},"sourceSize":{"w":383,"h":393}},"h3 (23).png":{"frame":{"x":366,"y":1032,"w":364,"h":371},"rotated":true,"trimmed":true,"spriteSourceSize":{"x":17,"y":20,"w":364,"h":371},"sourceSize":{"w":383,"h":393}},"h3 (22).png":{"frame":{"x":1144,"y":1061,"w":365,"h":373},"rotated":true,"trimmed":true,"spriteSourceSize":{"x":16,"y":20,"w":365,"h":373},"sourceSize":{"w":383,"h":393}},"h3 (21).png":{"frame":{"x":739,"y":1116,"w":366,"h":372},"rotated":true,"trimmed":true,"spriteSourceSize":{"x":15,"y":19,"w":366,"h":372},"sourceSize":{"w":383,"h":393}},"h3 (20).png":{"frame":{"x":1519,"y":2,"w":365,"h":378},"rotated":true,"trimmed":true,"spriteSourceSize":{"x":15,"y":12,"w":365,"h":378},"sourceSize":{"w":383,"h":393}},"h3 (2).png":{"frame":{"x":1113,"y":1428,"w":253,"h":258},"rotated":false,"trimmed":true,"spriteSourceSize":{"x":66,"y":70,"w":253,"h":258},"sourceSize":{"w":383,"h":393}},"h3 (19).png":{"frame":{"x":1519,"y":369,"w":367,"h":379},"rotated":true,"trimmed":true,"spriteSourceSize":{"x":16,"y":13,"w":367,"h":379},"sourceSize":{"w":383,"h":393}},"h3 (18).png":{"frame":{"x":1519,"y":738,"w":365,"h":378},"rotated":true,"trimmed":true,"spriteSourceSize":{"x":15,"y":13,"w":365,"h":378},"sourceSize":{"w":383,"h":393}},"h3 (17).png":{"frame":{"x":1519,"y":1105,"w":361,"h":378},"rotated":true,"trimmed":true,"spriteSourceSize":{"x":18,"y":15,"w":361,"h":378},"sourceSize":{"w":383,"h":393}},"h3 (16).png":{"frame":{"x":2,"y":1719,"w":359,"h":375},"rotated":true,"trimmed":true,"spriteSourceSize":{"x":18,"y":18,"w":359,"h":375},"sourceSize":{"w":383,"h":393}},"h3 (15).png":{"frame":{"x":379,"y":1688,"w":359,"h":377},"rotated":false,"trimmed":true,"spriteSourceSize":{"x":16,"y":16,"w":359,"h":377},"sourceSize":{"w":383,"h":393}},"h3 (14).png":{"frame":{"x":740,"y":1484,"w":356,"h":374},"rotated":false,"trimmed":true,"spriteSourceSize":{"x":20,"y":17,"w":356,"h":374},"sourceSize":{"w":383,"h":393}},"h3 (13).png":{"frame":{"x":1098,"y":1688,"w":362,"h":371},"rotated":false,"trimmed":true,"spriteSourceSize":{"x":14,"y":16,"w":362,"h":371},"sourceSize":{"w":383,"h":393}},"h3 (12).png":{"frame":{"x":1462,"y":1468,"w":355,"h":357},"rotated":true,"trimmed":true,"spriteSourceSize":{"x":20,"y":23,"w":355,"h":357},"sourceSize":{"w":383,"h":393}},"h3 (11).png":{"frame":{"x":1462,"y":1825,"w":253,"h":263},"rotated":true,"trimmed":true,"spriteSourceSize":{"x":66,"y":65,"w":253,"h":263},"sourceSize":{"w":383,"h":393}},"h3 (10).png":{"frame":{"x":366,"y":1398,"w":253,"h":263},"rotated":false,"trimmed":true,"spriteSourceSize":{"x":66,"y":65,"w":253,"h":263},"sourceSize":{"w":383,"h":393}},"h3 (1).png":{"frame":{"x":1727,"y":1825,"w":253,"h":259},"rotated":true,"trimmed":true,"spriteSourceSize":{"x":66,"y":69,"w":253,"h":259},"sourceSize":{"w":383,"h":393}}},"animations":{},"meta":{"app":"http://github.com/pixijs/assetpack","version":"1.0","image":"h3.webp","format":"RGBA8888","size":{"w":1988,"h":2080},"scale":1,"related_multi_packs":[]}}